{
    "number_of_non_significant_results": 20, 
    "number_of_significant_results": 16, 
    "actual_results": [
        {
            "statistic": 0.7654579969164176, 
            "x_label": "platoonSplitTime", 
            "y_parameter": "Overheads", 
            "means_of_x_parameters": [
                1.9890100309349028, 
                1.9649059433189184
            ], 
            "pvalue": 0.44418542618065315, 
            "x_parameters": [
                "3.0.json", 
                "4.0.json"
            ]
        }, 
        {
            "statistic": 2.0595232947706004, 
            "x_label": "platoonSplitTime", 
            "y_parameter": "Overheads", 
            "means_of_x_parameters": [
                1.9890100309349028, 
                1.92536375014471
            ], 
            "pvalue": 0.03971466835876939, 
            "x_parameters": [
                "3.0.json", 
                "5.0.json"
            ]
        }, 
        {
            "statistic": 0.471776538133663, 
            "x_label": "platoonSplitTime", 
            "y_parameter": "Overheads", 
            "means_of_x_parameters": [
                1.9890100309349028, 
                1.9736252239314545
            ], 
            "pvalue": 0.637194110786427, 
            "x_parameters": [
                "3.0.json", 
                "6.0.json"
            ]
        }, 
        {
            "statistic": 0.2794638137117269, 
            "x_label": "platoonSplitTime", 
            "y_parameter": "Overheads", 
            "means_of_x_parameters": [
                1.9890100309349028, 
                1.9799378297640815
            ], 
            "pvalue": 0.779950203772051, 
            "x_parameters": [
                "3.0.json", 
                "7.0.json"
            ]
        }, 
        {
            "statistic": 4.030375018853374, 
            "x_label": "platoonSplitTime", 
            "y_parameter": "Overheads", 
            "means_of_x_parameters": [
                1.9890100309349028, 
                1.860965185129256
            ], 
            "pvalue": 6.003382122239406e-05, 
            "x_parameters": [
                "3.0.json", 
                "8.0.json"
            ]
        }, 
        {
            "statistic": 0.8786773350922862, 
            "x_label": "platoonSplitTime", 
            "y_parameter": "Overheads", 
            "means_of_x_parameters": [
                1.9890100309349028, 
                1.961013813345046
            ], 
            "pvalue": 0.37979129449838, 
            "x_parameters": [
                "3.0.json", 
                "10.0.json"
            ]
        }, 
        {
            "statistic": 0.7799011654422321, 
            "x_label": "platoonSplitTime", 
            "y_parameter": "Overheads", 
            "means_of_x_parameters": [
                1.9890100309349028, 
                1.964033743675796
            ], 
            "pvalue": 0.43563951116568467, 
            "x_parameters": [
                "3.0.json", 
                "15.0.json"
            ]
        }, 
        {
            "statistic": -3.68702891111852, 
            "x_label": "platoonSplitTime", 
            "y_parameter": "Overheads", 
            "means_of_x_parameters": [
                1.9890100309349028, 
                2.1120496968466855
            ], 
            "pvalue": 0.00024006332050952782, 
            "x_parameters": [
                "3.0.json", 
                "20.0.json"
            ]
        }, 
        {
            "statistic": 1.3567368254962424, 
            "x_label": "platoonSplitTime", 
            "y_parameter": "Overheads", 
            "means_of_x_parameters": [
                1.9649059433189184, 
                1.92536375014471
            ], 
            "pvalue": 0.17517216432882052, 
            "x_parameters": [
                "4.0.json", 
                "5.0.json"
            ]
        }, 
        {
            "statistic": -0.28172907505095607, 
            "x_label": "platoonSplitTime", 
            "y_parameter": "Overheads", 
            "means_of_x_parameters": [
                1.9649059433189184, 
                1.9736252239314545
            ], 
            "pvalue": 0.7782118733299612, 
            "x_parameters": [
                "4.0.json", 
                "6.0.json"
            ]
        }, 
        {
            "statistic": -0.4881476733858919, 
            "x_label": "platoonSplitTime", 
            "y_parameter": "Overheads", 
            "means_of_x_parameters": [
                1.9649059433189184, 
                1.9799378297640815
            ], 
            "pvalue": 0.6255580034015085, 
            "x_parameters": [
                "4.0.json", 
                "7.0.json"
            ]
        }, 
        {
            "statistic": 3.4575056724676654, 
            "x_label": "platoonSplitTime", 
            "y_parameter": "Overheads", 
            "means_of_x_parameters": [
                1.9649059433189184, 
                1.860965185129256
            ], 
            "pvalue": 0.0005681395498075122, 
            "x_parameters": [
                "4.0.json", 
                "8.0.json"
            ]
        }, 
        {
            "statistic": 0.12905211023605212, 
            "x_label": "platoonSplitTime", 
            "y_parameter": "Overheads", 
            "means_of_x_parameters": [
                1.9649059433189184, 
                1.961013813345046
            ], 
            "pvalue": 0.8973421157912361, 
            "x_parameters": [
                "4.0.json", 
                "10.0.json"
            ]
        }, 
        {
            "statistic": 0.0287553896857746, 
            "x_label": "platoonSplitTime", 
            "y_parameter": "Overheads", 
            "means_of_x_parameters": [
                1.9649059433189184, 
                1.964033743675796
            ], 
            "pvalue": 0.9770654755302062, 
            "x_parameters": [
                "4.0.json", 
                "15.0.json"
            ]
        }, 
        {
            "statistic": -4.634511409937675, 
            "x_label": "platoonSplitTime", 
            "y_parameter": "Overheads", 
            "means_of_x_parameters": [
                1.9649059433189184, 
                2.1120496968466855
            ], 
            "pvalue": 4.095169019881645e-06, 
            "x_parameters": [
                "4.0.json", 
                "20.0.json"
            ]
        }, 
        {
            "statistic": -1.5900395847434787, 
            "x_label": "platoonSplitTime", 
            "y_parameter": "Overheads", 
            "means_of_x_parameters": [
                1.92536375014471, 
                1.9736252239314545
            ], 
            "pvalue": 0.11215853475285589, 
            "x_parameters": [
                "5.0.json", 
                "6.0.json"
            ]
        }, 
        {
            "statistic": -1.8074562450147236, 
            "x_label": "platoonSplitTime", 
            "y_parameter": "Overheads", 
            "means_of_x_parameters": [
                1.92536375014471, 
                1.9799378297640815
            ], 
            "pvalue": 0.07101163282432449, 
            "x_parameters": [
                "5.0.json", 
                "7.0.json"
            ]
        }, 
        {
            "statistic": 2.1868874054766323, 
            "x_label": "platoonSplitTime", 
            "y_parameter": "Overheads", 
            "means_of_x_parameters": [
                1.92536375014471, 
                1.860965185129256
            ], 
            "pvalue": 0.028982877542853197, 
            "x_parameters": [
                "5.0.json", 
                "8.0.json"
            ]
        }, 
        {
            "statistic": -1.206569818414138, 
            "x_label": "platoonSplitTime", 
            "y_parameter": "Overheads", 
            "means_of_x_parameters": [
                1.92536375014471, 
                1.961013813345046
            ], 
            "pvalue": 0.22788186625000054, 
            "x_parameters": [
                "5.0.json", 
                "10.0.json"
            ]
        }, 
        {
            "statistic": -1.301034306419584, 
            "x_label": "platoonSplitTime", 
            "y_parameter": "Overheads", 
            "means_of_x_parameters": [
                1.92536375014471, 
                1.964033743675796
            ], 
            "pvalue": 0.1935516684379649, 
            "x_parameters": [
                "5.0.json", 
                "15.0.json"
            ]
        }, 
        {
            "statistic": -5.989646887368458, 
            "x_label": "platoonSplitTime", 
            "y_parameter": "Overheads", 
            "means_of_x_parameters": [
                1.92536375014471, 
                2.1120496968466855
            ], 
            "pvalue": 3.034516212315184e-09, 
            "x_parameters": [
                "5.0.json", 
                "20.0.json"
            ]
        }, 
        {
            "statistic": -0.19764712829196301, 
            "x_label": "platoonSplitTime", 
            "y_parameter": "Overheads", 
            "means_of_x_parameters": [
                1.9736252239314545, 
                1.9799378297640815
            ], 
            "pvalue": 0.843364257287108, 
            "x_parameters": [
                "6.0.json", 
                "7.0.json"
            ]
        }, 
        {
            "statistic": 3.606942841306316, 
            "x_label": "platoonSplitTime", 
            "y_parameter": "Overheads", 
            "means_of_x_parameters": [
                1.9736252239314545, 
                1.860965185129256
            ], 
            "pvalue": 0.00032569419778783425, 
            "x_parameters": [
                "6.0.json", 
                "8.0.json"
            ]
        }, 
        {
            "statistic": 0.402565453318106, 
            "x_label": "platoonSplitTime", 
            "y_parameter": "Overheads", 
            "means_of_x_parameters": [
                1.9736252239314545, 
                1.961013813345046
            ], 
            "pvalue": 0.6873562209783639, 
            "x_parameters": [
                "6.0.json", 
                "10.0.json"
            ]
        }, 
        {
            "statistic": 0.3045539274961196, 
            "x_label": "platoonSplitTime", 
            "y_parameter": "Overheads", 
            "means_of_x_parameters": [
                1.9736252239314545, 
                1.964033743675796
            ], 
            "pvalue": 0.7607718761368695, 
            "x_parameters": [
                "6.0.json", 
                "15.0.json"
            ]
        }, 
        {
            "statistic": -4.212382765242732, 
            "x_label": "platoonSplitTime", 
            "y_parameter": "Overheads", 
            "means_of_x_parameters": [
                1.9736252239314545, 
                2.1120496968466855
            ], 
            "pvalue": 2.7771958126197592e-05, 
            "x_parameters": [
                "6.0.json", 
                "20.0.json"
            ]
        }, 
        {
            "statistic": 3.8279237138848234, 
            "x_label": "platoonSplitTime", 
            "y_parameter": "Overheads", 
            "means_of_x_parameters": [
                1.9799378297640815, 
                1.860965185129256
            ], 
            "pvalue": 0.00013765755927440496, 
            "x_parameters": [
                "7.0.json", 
                "8.0.json"
            ]
        }, 
        {
            "statistic": 0.6070439090278694, 
            "x_label": "platoonSplitTime", 
            "y_parameter": "Overheads", 
            "means_of_x_parameters": [
                1.9799378297640815, 
                1.961013813345046
            ], 
            "pvalue": 0.5439650226961326, 
            "x_parameters": [
                "7.0.json", 
                "10.0.json"
            ]
        }, 
        {
            "statistic": 0.5074563605967222, 
            "x_label": "platoonSplitTime", 
            "y_parameter": "Overheads", 
            "means_of_x_parameters": [
                1.9799378297640815, 
                1.964033743675796
            ], 
            "pvalue": 0.6119526406437419, 
            "x_parameters": [
                "7.0.json", 
                "15.0.json"
            ]
        }, 
        {
            "statistic": -4.038269646905261, 
            "x_label": "platoonSplitTime", 
            "y_parameter": "Overheads", 
            "means_of_x_parameters": [
                1.9799378297640815, 
                2.1120496968466855
            ], 
            "pvalue": 5.8422588476062846e-05, 
            "x_parameters": [
                "7.0.json", 
                "20.0.json"
            ]
        }, 
        {
            "statistic": -3.2854738799413647, 
            "x_label": "platoonSplitTime", 
            "y_parameter": "Overheads", 
            "means_of_x_parameters": [
                1.860965185129256, 
                1.961013813345046
            ], 
            "pvalue": 0.0010530904784856606, 
            "x_parameters": [
                "8.0.json", 
                "10.0.json"
            ]
        }, 
        {
            "statistic": -3.365779759457197, 
            "x_label": "platoonSplitTime", 
            "y_parameter": "Overheads", 
            "means_of_x_parameters": [
                1.860965185129256, 
                1.964033743675796
            ], 
            "pvalue": 0.00079253776873393, 
            "x_parameters": [
                "8.0.json", 
                "15.0.json"
            ]
        }, 
        {
            "statistic": -7.839654156742218, 
            "x_label": "platoonSplitTime", 
            "y_parameter": "Overheads", 
            "means_of_x_parameters": [
                1.860965185129256, 
                2.1120496968466855
            ], 
            "pvalue": 1.2405692752690503e-14, 
            "x_parameters": [
                "8.0.json", 
                "20.0.json"
            ]
        }, 
        {
            "statistic": -0.09831227243978082, 
            "x_label": "platoonSplitTime", 
            "y_parameter": "Overheads", 
            "means_of_x_parameters": [
                1.961013813345046, 
                1.964033743675796
            ], 
            "pvalue": 0.9217040126903415, 
            "x_parameters": [
                "10.0.json", 
                "15.0.json"
            ]
        }, 
        {
            "statistic": -4.7024463143946695, 
            "x_label": "platoonSplitTime", 
            "y_parameter": "Overheads", 
            "means_of_x_parameters": [
                1.961013813345046, 
                2.1120496968466855
            ], 
            "pvalue": 2.9585840945891174e-06, 
            "x_parameters": [
                "10.0.json", 
                "20.0.json"
            ]
        }, 
        {
            "statistic": -4.585313266725771, 
            "x_label": "platoonSplitTime", 
            "y_parameter": "Overheads", 
            "means_of_x_parameters": [
                1.964033743675796, 
                2.1120496968466855
            ], 
            "pvalue": 5.157433729410932e-06, 
            "x_parameters": [
                "15.0.json", 
                "20.0.json"
            ]
        }
    ]
}