{
    "averages": {
        "totalCO2EmissionAverage": 10729.825797308395, 
        "totalCOEmissionAverage": 279.1907742078359, 
        "totalFuelConsumptionAverage": 4.612277630129204, 
        "totalHCEmissionAverage": 1.551318422196353, 
        "totalNOxEmissionAverage": 4.531248409316892, 
        "totalNoiseEmissionAverage": 78.84528942981198, 
        "totalPMXEmissionAverage": 0.304450797957686, 
        "totalSpeedAverage": 39.92168757718959, 
        "totalTripAverage": 283.1957511380875
    }, 
    "config": {
        "catchupDist": 150.0, 
        "joinDistance": 100.0, 
        "lookAheadDistance": 200.0, 
        "maxPlatoonGap": 100.0, 
        "maxVehiclesInPlatoon": 7, 
        "nonPlatoonCarCounter": 200, 
        "nrOfNotTravelledEdges": 5, 
        "platoonCarCounter": 100, 
        "platoonSplitTime": 5.0, 
        "switchImpatienceFactor": 0.1
    }, 
    "nrOfPlatoonsFormed": 140, 
    "nrOfPlatoonsSplit": 116, 
    "overallPlatoonDuration": 6577, 
    "simTime": 2000.0, 
    "totalTrips": 658
}