{
    "averages": {
        "totalCO2EmissionAverage": 9579.370877867792, 
        "totalCOEmissionAverage": 251.66511149606092, 
        "totalFuelConsumptionAverage": 4.117751745304736, 
        "totalHCEmissionAverage": 1.3953673222342555, 
        "totalNOxEmissionAverage": 4.043667848860275, 
        "totalNoiseEmissionAverage": 76.3717356898437, 
        "totalPMXEmissionAverage": 0.2699705132710137, 
        "totalSpeedAverage": 35.62659892435734, 
        "totalTripAverage": 312.9879101899831
    }, 
    "config": {
        "catchupDist": 150.0, 
        "joinDistance": 100.0, 
        "lookAheadDistance": 200.0, 
        "maxPlatoonGap": 25.0, 
        "maxVehiclesInPlatoon": 6, 
        "nonPlatoonCarCounter": 200, 
        "nrOfNotTravelledEdges": 5, 
        "platoonCarCounter": 100, 
        "platoonSplitTime": 5.0, 
        "switchImpatienceFactor": 0.1
    }, 
    "nrOfPlatoonsFormed": 79, 
    "nrOfPlatoonsSplit": 84, 
    "overallPlatoonDuration": 1876, 
    "simTime": 2000.0, 
    "totalTrips": 578
}